jsoneditor/__init__.py
jsoneditor/forms.py
jsoneditor/fields/__init__.py
jsoneditor/fields/django3_jsonfield.py
jsoneditor/fields/django_extensions_jsonfield.py
jsoneditor/fields/django_json_field.py
jsoneditor/fields/django_jsonfield.py
jsoneditor/fields/jsonfield.py
jsoneditor/fields/postgres_jsonfield.py
jsoneditor/static/django-jsoneditor/ace_options.js
jsoneditor/static/django-jsoneditor/django-jsoneditor.css
jsoneditor/static/django-jsoneditor/django-jsoneditor.js
jsoneditor/static/django-jsoneditor/init.js
jsoneditor/static/jsoneditor/jsoneditor.css
jsoneditor/static/jsoneditor/jsoneditor.js
jsoneditor/static/jsoneditor/img/jsoneditor-icons.png
jsoneditor/static/jsoneditor/img/jsoneditor-icons.svg
django_jsoneditor-0.2.4.dist-info/LICENSE
django_jsoneditor-0.2.4.dist-info/METADATA
django_jsoneditor-0.2.4.dist-info/WHEEL
django_jsoneditor-0.2.4.dist-info/top_level.txt
django_jsoneditor-0.2.4.dist-info/RECORD
