Metadata-Version: 2.1
Name: django-jsoneditor
Version: 0.2.4
Summary: Django JSON Editor
Home-page: https://github.com/nnseva/django-jsoneditor
Author: Vsevolod Novikov
Author-email: nnseva@gmail.com
License-File: LICENSE
